ddstable/__init__.py
ddstable/dds-64.dll
ddstable/ddstable.py
ddstable/libdds.so
ddstable-0.2.0.dist-info/METADATA
ddstable-0.2.0.dist-info/WHEEL
ddstable-0.2.0.dist-info/top_level.txt
ddstable-0.2.0.dist-info/RECORD
