Metadata-Version: 2.1
Name: ddstable
Version: 0.2.0
Summary: DDS table for contract bridge
Home-page: https://gitlab.com/xrgopher/ddstable
Author: xrgopher
Author-email: xrgopher@outlook.com
License: UNKNOWN
Platform: UNKNOWN
Classifier: Programming Language :: Python :: 3
Classifier: License :: OSI Approved :: GNU General Public License v3 (GPLv3)
Classifier: Operating System :: OS Independent
Requires-Python: >=3.6
